pywe_decrypt/__init__.py
pywe_decrypt/code.py
pywe_decrypt/data.py
pywe_decrypt/msg.py
pywe_decrypt-1.1.7.dist-info/METADATA
pywe_decrypt-1.1.7.dist-info/WHEEL
pywe_decrypt-1.1.7.dist-info/top_level.txt
pywe_decrypt-1.1.7.dist-info/RECORD
