Metadata-Version: 2.1
Name: pywe-decrypt
Version: 1.1.7
Summary: Wechat Decrypt Module for Python.
Home-page: https://github.com/sdkwe/pywe-decrypt
Author: Hackathon
Author-email: kimi.huang@brightcells.com
License: UNKNOWN
Keywords: Wechat Weixin Decrypt
Platform: UNKNOWN
Classifier: License :: OSI Approved :: BSD License
Classifier: Programming Language :: Python
Classifier: Programming Language :: Python :: 2
Classifier: Programming Language :: Python :: 2.6
Classifier: Programming Language :: Python :: 2.7
Classifier: Programming Language :: Python :: 3
Classifier: Programming Language :: Python :: 3.2
Classifier: Programming Language :: Python :: 3.3
Classifier: Programming Language :: Python :: 3.4
Classifier: Topic :: Software Development :: Libraries :: Python Modules
Requires-Dist: pycryptodome
Requires-Dist: pywe-sign (>=1.0.8)
Requires-Dist: pywe-utils
Requires-Dist: pywe-xml (>=1.0.3)
